post_iter/__init__.py
post_iter-0.1.0.dist-info/WHEEL
post_iter-0.1.0.dist-info/METADATA
post_iter-0.1.0.dist-info/RECORD
