Metadata-Version: 2.1
Name: post-iter
Version: 0.1.0
Summary: 
Author: Aatif Syed
Author-email: aatifsyedyp@gmail.com
Requires-Python: >=3.8,<4.0
Classifier: Programming Language :: Python :: 3
Classifier: Programming Language :: Python :: 3.10
Classifier: Programming Language :: Python :: 3.8
Classifier: Programming Language :: Python :: 3.9
Requires-Dist: more-itertools (>=8.12.0,<9.0.0)
Requires-Dist: returns (>=0.18.0,<0.19.0)
